create_vars/__init__.py
create_vars/_modidx.py
create_vars/vars.py
create_vars-0.0.1.dist-info/LICENSE
create_vars-0.0.1.dist-info/METADATA
create_vars-0.0.1.dist-info/WHEEL
create_vars-0.0.1.dist-info/entry_points.txt
create_vars-0.0.1.dist-info/top_level.txt
create_vars-0.0.1.dist-info/RECORD
